[
    {
        "key": "dbln",
        "value": "%7B%2261564141001507%22%3A%22f3UyAXR2%22%7D",
        "domain": "facebook.com",
        "path": "/login/device-based/",
        "hostOnly": false,
        "creation": "2024-10-30T10:44:24.164Z",
        "lastAccessed": "2024-10-30T10:44:24.164Z"
    },
    {
        "key": "datr",
        "value": "qNohZ-P7zKpeCh0MupRDkZXX",
        "domain": "facebook.com",
        "path": "/",
        "hostOnly": false,
        "creation": "2024-10-30T10:44:24.164Z",
        "lastAccessed": "2024-10-30T10:44:24.164Z"
    },
    {
        "key": "sb",
        "value": "qNohZ4hIMknaBpko7sn2g2P5",
        "domain": "facebook.com",
        "path": "/",
        "hostOnly": false,
        "creation": "2024-10-30T10:44:24.164Z",
        "lastAccessed": "2024-10-30T10:44:24.164Z"
    },
    {
        "key": "locale",
        "value": "en_US",
        "domain": "facebook.com",
        "path": "/",
        "hostOnly": false,
        "creation": "2024-10-30T10:44:24.164Z",
        "lastAccessed": "2024-10-30T10:44:24.164Z"
    },
    {
        "key": "vpd",
        "value": "v1%3B1032x522x1.381250023841858",
        "domain": "facebook.com",
        "path": "/",
        "hostOnly": false,
        "creation": "2024-10-30T10:44:24.164Z",
        "lastAccessed": "2024-10-30T10:44:24.164Z"
    },
    {
        "key": "c_user",
        "value": "61564141001507",
        "domain": "facebook.com",
        "path": "/",
        "hostOnly": false,
        "creation": "2024-10-30T10:44:24.164Z",
        "lastAccessed": "2024-10-30T10:44:24.164Z"
    },
    {
        "key": "fr",
        "value": "0RcHOuojRZL8zEiUB.AWWztatz0tblQoV4Zmg4aoYNxQs.BnIdqo..AAA.0.0.BnIg19.AWWp_J1IVug",
        "domain": "facebook.com",
        "path": "/",
        "hostOnly": false,
        "creation": "2024-10-30T10:44:24.164Z",
        "lastAccessed": "2024-10-30T10:44:24.164Z"
    },
    {
        "key": "xs",
        "value": "1%3AFiG7U5zH2HU3Sw%3A2%3A1730284926%3A-1%3A5364",
        "domain": "facebook.com",
        "path": "/",
        "hostOnly": false,
        "creation": "2024-10-30T10:44:24.164Z",
        "lastAccessed": "2024-10-30T10:44:24.164Z"
    },
    {
        "key": "wd",
        "value": "523x1032",
        "domain": "facebook.com",
        "path": "/",
        "hostOnly": false,
        "creation": "2024-10-30T10:44:24.164Z",
        "lastAccessed": "2024-10-30T10:44:24.164Z"
    },
    {
        "key": "fbl_st",
        "value": "100437032%3BT%3A28838084",
        "domain": "facebook.com",
        "path": "/",
        "hostOnly": false,
        "creation": "2024-10-30T10:44:24.164Z",
        "lastAccessed": "2024-10-30T10:44:24.164Z"
    },
    {
        "key": "wl_cbv",
        "value": "v2%3Bclient_version%3A2658%3Btimestamp%3A1730285058",
        "domain": "facebook.com",
        "path": "/",
        "hostOnly": false,
        "creation": "2024-10-30T10:44:24.164Z",
        "lastAccessed": "2024-10-30T10:44:24.164Z"
    }
]
